qrdata/__init__.py
qrdata/enums.py
qrdata/inputdata.py
qrdata/logger.py
qrdata/main.py
qrdata/qrcode_data.py
qrdata/qrcode_generator.py
qrdata/qrdata_ui.py
qrdata/data/qrcode.csv
qrdata-0.0.2.dist-info/METADATA
qrdata-0.0.2.dist-info/WHEEL
qrdata-0.0.2.dist-info/entry_points.txt
qrdata-0.0.2.dist-info/top_level.txt
qrdata-0.0.2.dist-info/RECORD
